slowPaste/__init__.py
slowPaste/slow_paste.py
slowPaste-0.6.dist-info/LICENSE
slowPaste-0.6.dist-info/METADATA
slowPaste-0.6.dist-info/WHEEL
slowPaste-0.6.dist-info/top_level.txt
slowPaste-0.6.dist-info/RECORD
