Metadata-Version: 2.1
Name: slowPaste
Version: 0.6
Summary: A Python package to simulate human-like typing with adjustable speed.
Home-page: https://github.com/robbiebusinessacc
Author: Robbie Walmsley
Author-email: robbiebusinessacc@gmail.com
License: MIT
Classifier: Development Status :: 3 - Alpha
Classifier: Intended Audience :: Developers
Classifier: License :: OSI Approved :: MIT License
Classifier: Programming Language :: Python :: 3
Classifier: Programming Language :: Python :: 3.6
Classifier: Programming Language :: Python :: 3.7
Classifier: Programming Language :: Python :: 3.8
Classifier: Programming Language :: Python :: 3.9
License-File: LICENSE
Requires-Dist: pyperclip
Requires-Dist: pyautogui
Requires-Dist: keyboard
